CONTRIBUTING.rst
CONTRIBUTORS.rst
HISTORY.rst
LICENSE
README.rst
docs/Makefile
docs/background.rst
docs/conf.py
docs/contributing.rst
docs/contributors.rst
docs/history.rst
docs/index.rst
docs/installation.rst
docs/make.bat
docs/readme.rst
docs/reference.rst
docs/usage.rst
sevivi/__init__.py
sevivi/config/__init__.py
sevivi/config/column_matching.py
sevivi/config/config_reader.py
sevivi/config/config_types/__init__.py
sevivi/config/config_types/config.py
sevivi/config/config_types/plotting_method.py
sevivi/config/config_types/render_config.py
sevivi/config/config_types/sensor_config.py
sevivi/config/config_types/stacking_direction.py
sevivi/config/config_types/video_config.py
sevivi/image_provider/__init__.py
sevivi/image_provider/dimensions.py
sevivi/image_provider/graph_provider/__init__.py
sevivi/image_provider/graph_provider/graph_provider.py
sevivi/image_provider/graph_provider/utils.py
sevivi/image_provider/video_provider/__init__.py
sevivi/image_provider/video_provider/azure_connections.py
sevivi/image_provider/video_provider/azure_image_provider.py
sevivi/image_provider/video_provider/imu_camera_image_provider.py
sevivi/image_provider/video_provider/plain_video_image_provider.py
sevivi/image_provider/video_provider/video_imu_capture_app/__init__.py
sevivi/image_provider/video_provider/video_imu_capture_app/recording_pb2.py
sevivi/image_provider/video_provider/video_imu_capture_app/video_imu_capture_app_image_provider.py
sevivi/image_provider/video_provider/video_provider.py
sevivi/log.py
sevivi/main.py
sevivi/synchronizer/__init__.py
sevivi/synchronizer/signal_processing.py
sevivi/synchronizer/synchronizer.py
sevivi/video_renderer/__init__.py
sevivi/video_renderer/instantiation_helpers.py
sevivi/video_renderer/progress_bar.py
sevivi/video_renderer/video_renderer.py
tests/__init__.py
tests/conftest.py
tests/test_config.py
tests/test_config_reader.py
tests/test_examples.py
tests/test_graph_provider.py
tests/test_image_provider.py
sevivi-1.0.3.dist-info/entry_points.txt
sevivi-1.0.3.dist-info/LICENSE
sevivi-1.0.3.dist-info/WHEEL
sevivi-1.0.3.dist-info/METADATA
sevivi-1.0.3.dist-info/RECORD
